fle_2d/__init__.py
fle_2d/fle_2d.py
fle_2d/jn_zeros_n=3000_nt=2500.mat
fle_2d-0.1.2.dist-info/licenses/LICENSE
fle_2d-0.1.2.dist-info/METADATA
fle_2d-0.1.2.dist-info/WHEEL
fle_2d-0.1.2.dist-info/top_level.txt
fle_2d-0.1.2.dist-info/RECORD
