Metadata-Version: 2.4
Name: fle_2d
Version: 0.1.2
Summary: Fast expansion into harmonics on the disk
Author: Nicholas F. Marshall
License:    MIT License
Classifier: Programming Language :: Python :: 3
Classifier: License :: OSI Approved :: MIT License
Classifier: Operating System :: OS Independent
Requires-Python: >=3.7
License-File: LICENSE
Dynamic: license-file
